mcp_jamie_test/__init__.py
mcp_jamie_test/main.py
mcp_jamie_test-0.1.0.dist-info/METADATA
mcp_jamie_test-0.1.0.dist-info/WHEEL
mcp_jamie_test-0.1.0.dist-info/entry_points.txt
mcp_jamie_test-0.1.0.dist-info/RECORD
