Metadata-Version: 2.4
Name: mcp-jamie-test
Version: 0.1.0
Summary: Add your description here
Author-email: jamiezhen <jamiezhen@tencent.com>
Requires-Python: >=3.13
Requires-Dist: httpx>=0.28.1
Requires-Dist: mcp[cli]>=1.6.0
Requires-Dist: openai>=1.76.0
Requires-Dist: requests>=2.32.3
